dsf_aml_sdk/__init__.py
dsf_aml_sdk/client.py
dsf_aml_sdk/exceptions.py
dsf_aml_sdk/models.py
dsf_aml_sdk-2.1.12.dist-info/licenses/LICENSE.txt
dsf_aml_sdk-2.1.12.dist-info/METADATA
dsf_aml_sdk-2.1.12.dist-info/WHEEL
dsf_aml_sdk-2.1.12.dist-info/top_level.txt
dsf_aml_sdk-2.1.12.dist-info/RECORD
