Metadata-Version: 2.4
Name: dsf-aml-sdk
Version: 2.1.12
Summary: DSF AML SDK — Automated ML Robustness & Failure Correction Framework
Home-page: https://dsfuptech.cloud
Author: Jaime Alexander Jimenez
Author-email: contacto@dsfuptech.cloud
License: Proprietary
Keywords: dsf aml ml machine-learning robustness auto-healing sdk
Classifier: Development Status :: 5 - Production/Stable
Classifier: Intended Audience :: Developers
Classifier: Topic :: Scientific/Engineering :: Artificial Intelligence
Classifier: License :: Other/Proprietary License
Classifier: Programming Language :: Python :: 3
Classifier: Programming Language :: Python :: 3.8
Classifier: Programming Language :: Python :: 3.9
Classifier: Programming Language :: Python :: 3.10
Classifier: Programming Language :: Python :: 3.11
Requires-Python: >=3.8
License-File: LICENSE.txt
Requires-Dist: requests>=2.25.0
Dynamic: author
Dynamic: author-email
Dynamic: classifier
Dynamic: description
Dynamic: description-content-type
Dynamic: home-page
Dynamic: keywords
Dynamic: license
Dynamic: license-file
Dynamic: requires-dist
Dynamic: requires-python
Dynamic: summary
